hoststats/__init__.py
hoststats/app.py
hoststats/cli.py
hoststats/client.py
hoststats/collection.py
hoststats/results.py
hoststats/server.py
hoststats/stats.py
hoststats/validation.py
hoststats-0.1.1.dist-info/LICENSE
hoststats-0.1.1.dist-info/METADATA
hoststats-0.1.1.dist-info/WHEEL
hoststats-0.1.1.dist-info/entry_points.txt
hoststats-0.1.1.dist-info/top_level.txt
hoststats-0.1.1.dist-info/RECORD
