Metadata-Version: 2.1
Name: hoststats
Version: 0.1.1
Summary: Host stats
Home-page: https://github.com/Shillaker/hoststats
Author: Simon Shillaker
Author-email: foo@bar.com
License: UNKNOWN
Platform: UNKNOWN
Requires-Python: >=3.6
License-File: LICENSE
Requires-Dist: click
Requires-Dist: flask
Requires-Dist: numpy
Requires-Dist: pandas
Requires-Dist: psutil
Requires-Dist: requests
